rattleSNP/VERSION
rattleSNP/__init__.py
rattleSNP/_version.py
rattleSNP/global_variables.py
rattleSNP/main.py
rattleSNP/rattleSNP-complete.sh
rattleSNP/rattleSNP_logo.png
rattleSNP/snakemake_module.py
rattleSNP/containers/Dockerfile_test
rattleSNP/containers/Singularity.rattleSNP_tools.def
rattleSNP/containers/Singularity.report.def
rattleSNP/default_profile/CookieCutter.py
rattleSNP/default_profile/slurm-sidecar.py
rattleSNP/default_profile/slurm-status.py
rattleSNP/default_profile/slurm-submit.py
rattleSNP/default_profile/slurm_utils.py
rattleSNP/install_files/cluster_config_SLURM.yaml
rattleSNP/install_files/config.yaml
rattleSNP/install_files/tools_path.yaml
rattleSNP/install_files/config_test/config_CMSR.yaml
rattleSNP/scripts/__init__.py
rattleSNP/scripts/vcf2geno.py
rattleSNP/scripts/vcf2phylip.py
rattleSNP/snakefiles/Snakefile
rattleSNP/snakefiles/mapping_stat.snake
rattleSNP/snakemake_scripts/rattleSNP_module.py
rattleSNP/snakemake_scripts/report.Rmd
rattleSNP/snakemake_scripts/report_vcf.Rmd
rattleSNP-1.1.0.dist-info/LICENCE
rattleSNP-1.1.0.dist-info/METADATA
rattleSNP-1.1.0.dist-info/WHEEL
rattleSNP-1.1.0.dist-info/entry_points.txt
rattleSNP-1.1.0.dist-info/top_level.txt
rattleSNP-1.1.0.dist-info/RECORD
