Metadata-Version: 2.1
Name: rattleSNP
Version: 1.1.0
Summary: RattleSNP is mapping workflow!!!!!
Author-email: "Ravel Sebastien (CIRAD)" <sebastien.ravel@cirad.fr>
License: GNU GENERAL PUBLIC LICENSE
Project-URL: Homepage, https://forge.ird.fr/phim/sravel/RattleSNP
Project-URL: Documentation, https://rattlesnp.readthedocs.io/en/latest/
Project-URL: repository, https://forge.ird.fr/phim/sravel/RattleSNP.git
Project-URL: Bug Tracker, https://forge.ird.fr/phim/sravel/RattleSNP/issues
Project-URL: Source Code, https://forge.ird.fr/phim/sravel/RattleSNP
Keywords: snakemake,SNP calling,workflow
Classifier: License :: OSI Approved :: GNU General Public License v3 or later (GPLv3+)
Classifier: License :: CeCILL-C Free Software License Agreement (CECILL-C)
Classifier: License :: Free for non-commercial use
Classifier: Development Status :: 5 - Production/Stable
Classifier: Intended Audience :: Developers
Classifier: Intended Audience :: End Users/Desktop
Classifier: Operating System :: POSIX :: Linux
Classifier: Programming Language :: Python :: 3.8
Classifier: Programming Language :: Python :: 3.9
Classifier: Programming Language :: R
Classifier: Natural Language :: English
Classifier: Topic :: Scientific/Engineering
Classifier: Topic :: Scientific/Engineering :: Bio-Informatics
Requires-Python: >=3.8
License-File: LICENCE
Requires-Dist: PyYAML
Requires-Dist: click (>=8.0.3)
Requires-Dist: pandas
Requires-Dist: matplotlib
Requires-Dist: tabulate
Requires-Dist: biopython
Requires-Dist: numpy
Requires-Dist: argparse
Requires-Dist: snakemake
Requires-Dist: tqdm
Requires-Dist: cookiecutter
Requires-Dist: docutils
Requires-Dist: snakecdysis
Provides-Extra: docs
Requires-Dist: sphinx ; extra == 'docs'
Requires-Dist: sphinx-click ; extra == 'docs'
Requires-Dist: sphinx-copybutton ; extra == 'docs'
Requires-Dist: sphinx-rtd-theme ; extra == 'docs'
Requires-Dist: tox ; extra == 'docs'
